reasoner_transpiler/attribute_types.json
reasoner_transpiler/attributes.py
reasoner_transpiler/biolink.py
reasoner_transpiler/cypher.py
reasoner_transpiler/cypher_expression.py
reasoner_transpiler/exceptions.py
reasoner_transpiler/matching.py
reasoner_transpiler/nesting.py
reasoner_transpiler/util.py
reasoner_transpiler-2.3.5.dist-info/METADATA
reasoner_transpiler-2.3.5.dist-info/WHEEL
reasoner_transpiler-2.3.5.dist-info/top_level.txt
reasoner_transpiler-2.3.5.dist-info/RECORD
