Metadata-Version: 2.4
Name: reasoner-transpiler
Version: 2.3.5
Summary: TRAPI → Cypher transpiler
Home-page: https://github.com/ranking-agent/reasoner-transpiler
Author: Patrick Wang
Author-email: patrick@covar.com
Maintainer: Evan Morris
Maintainer-email: emorris@renci.org
License: MIT
Requires-Python: >=3.9
Requires-Dist: bmt==1.4.4
Dynamic: author
Dynamic: author-email
Dynamic: description
Dynamic: description-content-type
Dynamic: home-page
Dynamic: license
Dynamic: maintainer
Dynamic: maintainer-email
Dynamic: requires-dist
Dynamic: requires-python
Dynamic: summary
